lightudq/__init__.py
lightudq/document_quality.py
lightudq/prompts.py
lightudq/schemas.py
lightudq/utils.py
lightudq-0.1.4.dist-info/METADATA
lightudq-0.1.4.dist-info/WHEEL
lightudq-0.1.4.dist-info/licenses/LICENSE
lightudq-0.1.4.dist-info/RECORD
