Metadata-Version: 2.4
Name: lightudq
Version: 0.1.4
Summary: assess unstructured data quality
Project-URL: Homepage, https://github.com/lightup-data/lightudq
Project-URL: Repository, https://github.com/lightup-data/lightudq
Project-URL: Documentation, https://github.com/lightup-data/lightudq#readme
Project-URL: Issue Tracker, https://github.com/lightup-data/lightudq/issues
Author-email: Sarabjot Singh <sarabjot@lightup.ai>
License-File: LICENSE
Requires-Python: >=3.9
Requires-Dist: dotenv>=0.9.9
Requires-Dist: pdoc>=15.0.4
Requires-Dist: pre-commit>=4.2.0
Requires-Dist: pydantic-ai>=0.2.16
Requires-Dist: pydantic>=2.11.5
Requires-Dist: pymupdf>=1.26.0
Requires-Dist: pytest>=8.4.0
Requires-Dist: twine>=6.1.0
